hip_controller/__init__.py
hip_controller/__main__.py
hip_controller/app.py
hip_controller/definitions.py
hip_controller/math_utils.py
hip_controller/utils.py
hip_controller/control/__init__.py
hip_controller/control/high_level.py
hip_controller/control/kalman.py
hip_controller/control/low_level.py
hip_controller/control/state_space.py
hip_controller-0.0.3.dist-info/METADATA
hip_controller-0.0.3.dist-info/WHEEL
hip_controller-0.0.3.dist-info/licenses/LICENSE
hip_controller-0.0.3.dist-info/RECORD
