Metadata-Version: 2.4
Name: hip_controller
Version: 0.0.3
Summary: Lower limb exosuit hip controller.
Project-URL: homepage, https://github.com/TUM-Aries-Lab/hip-controller
Author-email: Tsmorz <tony.smoragiewicz@tum.de>
License-File: LICENSE
Requires-Python: <3.14,>=3.11
Requires-Dist: loguru>=0.7.3
Requires-Dist: numpy>=2.2.3
Requires-Dist: pandas>=2.3.3
Requires-Dist: scipy>=1.16.3
Provides-Extra: dev
Requires-Dist: coveralls>=4.0.1; extra == 'dev'
Requires-Dist: darglint>=1.8.1; extra == 'dev'
Requires-Dist: openpyxl==3.1.5; extra == 'dev'
Requires-Dist: pre-commit>=4.1.0; extra == 'dev'
Requires-Dist: pyright>=1.1.408; extra == 'dev'
Requires-Dist: pytest-cov>=6.0; extra == 'dev'
Requires-Dist: pytest>=8.3; extra == 'dev'
Requires-Dist: ruff>=0.6.9; extra == 'dev'
Provides-Extra: hw
Provides-Extra: no-hw
